region/__init__.py
region/api.py
region/csgraph_utils.py
region/objective_function.py
region/util.py
region/max_p_regions/__init__.py
region/max_p_regions/api.py
region/max_p_regions/exact.py
region/max_p_regions/heuristics.py
region/max_p_regions/tests/__init__.py
region/max_p_regions/tests/data.py
region/max_p_regions/tests/test_exact.py
region/max_p_regions/tests/test_heu.py
region/p_regions/__init__.py
region/p_regions/api.py
region/p_regions/azp.py
region/p_regions/azp_util.py
region/p_regions/exact.py
region/p_regions/tests/__init__.py
region/p_regions/tests/data.py
region/p_regions/tests/test_azp.py
region/p_regions/tests/test_azp_basic_tabu.py
region/p_regions/tests/test_azp_reactive_tabu.py
region/p_regions/tests/test_azp_simulated_annealing.py
region/p_regions/tests/test_exact.py
region/skater/__init__.py
region/skater/__version__.py
region/skater/skater.py
region/skater/test_skater.py
region/tests/__init__.py
region/tests/test_util.py
region/tests/util.py
region-0.2.1.dist-info/LICENSE.txt
region-0.2.1.dist-info/METADATA
region-0.2.1.dist-info/WHEEL
region-0.2.1.dist-info/top_level.txt
region-0.2.1.dist-info/RECORD
