Metadata-Version: 2.1
Name: region
Version: 0.2.1
Summary: Package offering regionalization algorithms
Home-page: https://github.com/pysal/region
Maintainer: PySAL Developers
Maintainer-email: pysal-dev@googlegroups.com
License: BSD 3-clause
Keywords: regionalization spatial clustering
Platform: UNKNOWN
Classifier: Development Status :: 3 - Alpha
Classifier: Intended Audience :: Science/Research
Classifier: Intended Audience :: Developers
Classifier: Intended Audience :: Education
Classifier: Topic :: Scientific/Engineering
Classifier: Topic :: Scientific/Engineering :: GIS
Classifier: License :: OSI Approved :: BSD License
Classifier: Programming Language :: Python :: 3
Classifier: Programming Language :: Python :: 3.5
Classifier: Programming Language :: Python :: 3.6
Requires-Python: >3.4
Requires-Dist: geopandas
Requires-Dist: libpysal
Requires-Dist: networkx (>=2.0.0)
Requires-Dist: numpy (>=1.10.4)
Requires-Dist: pulp
Requires-Dist: pytest
Requires-Dist: scipy
Requires-Dist: sklearn
